Metadata-Version: 2.1
Name: PyAmazonWebScraper
Version: 0.0.5
Summary: Python Web Scraper : Pranav Sai
Home-page: 
Author: Pranav Sai
Author-email: pranavs31899@gmail.com
License: MIT
Keywords: Python Web Scraper
Platform: UNKNOWN
Classifier: Development Status :: 5 - Production/Stable
Classifier: Intended Audience :: Education
Classifier: Operating System :: Microsoft :: Windows :: Windows 10
Classifier: License :: OSI Approved :: MIT License
Classifier: Programming Language :: Python :: 3
License-File: LICENCE.txt
